shellfire/__init__.py
shellfire/commands.py
shellfire/config.py
shellfire/payloads.py
shellfire/plugin_collection.py
shellfire/default_plugins/__init__.py
shellfire/default_plugins/default.py
shellfire-0.13.dist-info/LICENSE
shellfire-0.13.dist-info/METADATA
shellfire-0.13.dist-info/WHEEL
shellfire-0.13.dist-info/entry_points.txt
shellfire-0.13.dist-info/top_level.txt
shellfire-0.13.dist-info/RECORD
